hcdk_utils/__init__.py
hcdk_utils/halloumi_alarms.py
hcdk_utils/halloumi_database_alarms.py
hcdk_utils/halloumi_documentdb_alarms.py
hcdk_utils/halloumi_elasticache_alarms.py
hcdk_utils/halloumi_mq_alarms.py
hcdk_utils/halloumi_oidc.py
hcdk_utils/halloumi_rds_snapshot_alarms.py
hcdk_utils/halloumi_users.py
hcdk_utils/halloumi_vpc_alarms.py
hcdk_utils/utils/__init__.py
hcdk_utils/utils/check_cdk.py
hcdk_utils/utils/functions.py
hcdk_utils/utils/hcdk_config.py
hcdk_utils/utils/parameters.py
utils/__init__.py
utils/check_cdk.py
utils/functions.py
utils/hcdk_config.py
utils/parameters.py
hcdk_utils-1.60.13.dist-info/LICENSE
hcdk_utils-1.60.13.dist-info/METADATA
hcdk_utils-1.60.13.dist-info/WHEEL
hcdk_utils-1.60.13.dist-info/top_level.txt
hcdk_utils-1.60.13.dist-info/RECORD
