Metadata-Version: 2.1
Name: hcdk-utils
Version: 1.60.13
Summary: General utility library for CDK projects
Home-page: https://github.com/sentiampc/hcdk-utils
License: UNKNOWN
Platform: UNKNOWN
Classifier: Programming Language :: Python :: 3
Classifier: License :: OSI Approved :: MIT License
Classifier: Operating System :: OS Independent
Requires-Dist: aws-cdk.aws-secretsmanager (>=1.61.1)
Requires-Dist: aws-cdk.aws-cloudwatch (>=1.61.1)
Requires-Dist: aws-cdk.aws-cloudwatch-actions (>=1.61.1)
Requires-Dist: aws-cdk.aws-docdb (>=1.61.1)
Requires-Dist: aws-cdk.aws-ec2 (>=1.61.1)
Requires-Dist: aws-cdk.aws-rds (>=1.61.1)
Requires-Dist: aws-cdk.aws-sns (>=1.61.1)
Requires-Dist: aws-cdk.core (>=1.61.1)
Requires-Dist: deepmerge
Requires-Dist: pyyaml
